MANIFEST.in
README.md
setup.py
starlette_swagger/__init__.py
starlette_swagger.egg-info/PKG-INFO
starlette_swagger.egg-info/SOURCES.txt
starlette_swagger.egg-info/dependency_links.txt
starlette_swagger.egg-info/not-zip-safe
starlette_swagger.egg-info/requires.txt
starlette_swagger.egg-info/top_level.txt
starlette_swagger/static/swagger-ui-bundle.js
starlette_swagger/static/swagger-ui.css