Metadata-Version: 2.1
Name: starlette-swagger
Version: 0.12
Summary: swagger ui for starlette
Home-page: https://github.com/zpdev/starlette-swagger
Author: zpzhou
Author-email: himoker@163.com
License: BSD
Platform: UNKNOWN
